{
  "generated": "2026-07-12T05:02:13.232693+00:00",
  "date": "2026-07-12",
  "count": 116,
  "articles": [
    {
      "source": "Schaffhauser Nachrichten",
      "title": "Link-Test",
      "url": "https://www.shn.ch/sport/wintersport/2026-07-12/link-test",
      "summary": "",
      "published": "2026-07-11T22:33:01.285119+00:00"
    },
    {
      "source": "Zentralplus",
      "title": "Klitschko warnt vor mehr Angriffen",
      "url": "https://www.zentralplus.ch/news/klitschko-warnt-vor-mehr-angriffen-2884356/",
      "summary": "Der Kiewer Bürgermeister Vitali Klitschko warnt vor mehr russischen Angriffen auf die ukrainische Hauptstadt. Er habe so etwas seit Kriegsbeginn noch nicht erlebt, so Klitschko angesichts mehrerer sch",
      "published": "2026-07-11T23:02:48.879101+00:00"
    },
    {
      "source": "Watson",
      "title": "WM 2026: England-Tor hätte aus kuriosem Grund nicht zählen dürfen",
      "url": "https://www.watson.ch/sport/fussball/730345967-wm-2026-england-tor-haette-aus-kuriosem-grund-nicht-zaehlen-duerfen",
      "summary": "",
      "published": "2026-07-11T23:02:48.879101+00:00"
    },
    {
      "source": "Basler Zeitung",
      "title": "Vom historischen Viertelfinal: Wie Morgenstreich im Sommer – so fiebert Basel in dieser Freinacht mit der Nati mit",
      "url": "https://www.bazonline.ch/schweiz-gegen-argentinien-so-fiebert-basel-mit-der-nati-mit-699508801070",
      "summary": "Wird ein Sommermärchen wahr? In wenigen Stunden wissen wir es. Bis dahin berichten wir live aus der Stadt.",
      "published": "2026-07-11T23:32:30.004909+00:00"
    },
    {
      "source": "Zentralplus",
      "title": "Iran: Strasse von Hormus wieder zu",
      "url": "https://www.zentralplus.ch/news/iran-strasse-von-hormus-wieder-zu-2884358/",
      "summary": "Die iranischen Revolutionsgarden haben die Strasse von Hormus bis auf Weiteres wieder für den gesamten Schiffsverkehr gesperrt. Das teilten sie am frühen Sonntagmorgen über die Staatsmedien mit. Grund",
      "published": "2026-07-11T23:32:30.004909+00:00"
    },
    {
      "source": "Watson",
      "title": "Klitschko warnt vor Zunahme russischer Angriffe auf Kiew",
      "url": "https://www.watson.ch/international/russland/113054347-klitschko-warnt-vor-zunahme-russischer-angriffe-auf-kiew",
      "summary": "",
      "published": "2026-07-11T23:32:30.004909+00:00"
    },
    {
      "source": "Watson",
      "title": "WM 2026: Schweiz trifft im Viertelfinal auf Argentinien – im Liveticker",
      "url": "https://www.watson.ch/sport/liveticker/668192912-wm-2026-schweiz-trifft-im-viertelfinal-auf-argentinien-im-liveticker",
      "summary": "",
      "published": "2026-07-11T23:32:30.004909+00:00"
    },
    {
      "source": "NZZ",
      "title": "LIVE-TICKER - Schafft die Schweiz die Sensation im WM-Viertelfinale gegen Argentinien? Mit dieser Aufstellung soll der Coup gelingen",
      "url": "https://www.nzz.ch/sport/schafft-die-schweiz-die-sensation-im-wm-viertelfinale-gegen-argentinien-mit-dieser-aufstellung-soll-der-coup-gelingen-ld.10015046",
      "summary": "",
      "published": "2026-07-11T23:51:32.329132+00:00"
    },
    {
      "source": "Watson",
      "title": "Iran schliesst Strasse von Hormus – Warnschüsse auf Schiff",
      "url": "https://www.watson.ch/international/iran/295509659-iran-schliesst-strasse-von-hormus-warnschuesse-auf-schiff",
      "summary": "",
      "published": "2026-07-11T23:51:32.329132+00:00"
    },
    {
      "source": "Watson",
      "title": "Konstantin Wecker erwirkt Verbot von Enthüllungsbericht",
      "url": "https://www.watson.ch/leben/deutschland/129368850-konstantin-wecker-erwirkt-verbot-von-enthuellungsbericht",
      "summary": "",
      "published": "2026-07-11T23:51:32.329132+00:00"
    },
    {
      "source": "Watson",
      "title": "Iran schliesst Strasse von Hormus – Warnschuss auf Schiff",
      "url": "https://www.watson.ch/international/iran/859719386-iran-schliesst-strasse-von-hormus-warnschuss-auf-schiff",
      "summary": "",
      "published": "2026-07-11T23:51:32.329132+00:00"
    },
    {
      "source": "Bote der Urschweiz",
      "title": "Nati-Aufstellung ist da: Vargas auf der Bank, Sow darf beginnen – Schweizer Halbfinal-Gegner bekannt",
      "url": "https://www.bote.ch/nachrichten/sport/schweiz-argentinien-liveticker-wm-viertelfinal-2026-art-1712413",
      "summary": "",
      "published": "2026-07-11T23:51:32.329132+00:00"
    },
    {
      "source": "Watson",
      "title": "WM 2026: England trifft im Viertelfinal auf Norwegen – im Liveticker",
      "url": "https://www.watson.ch/sport/fussball/828483353-wm-2026-england-trifft-im-viertelfinal-auf-norwegen-im-liveticker",
      "summary": "",
      "published": "2026-07-12T00:02:18.399513+00:00"
    },
    {
      "source": "Nebelspalter",
      "title": "Ist Krieg Nützlich oder Nutzlos",
      "url": "https://www.nebelspalter.ch/themen/2026/07/ist-krieg-nuetzlich-oder-nutzlos",
      "summary": "",
      "published": "2026-07-12T00:32:31.095890+00:00"
    },
    {
      "source": "Nebelspalter",
      "title": "Iv Defizit Zunahme von Psychischen Erkrankungen",
      "url": "https://www.nebelspalter.ch/themen/2026/07/iv-defizit-zunahme-von-psychischen-erkrankungen",
      "summary": "",
      "published": "2026-07-12T00:32:31.095890+00:00"
    },
    {
      "source": "Watson",
      "title": "Das gilt wegen der Hitzewelle jetzt für Bars und Restaurants in Spanien",
      "url": "https://www.watson.ch/international/reisen/627225249-das-gilt-wegen-der-hitzewelle-jetzt-fuer-bars-und-restaurants-in-spanien",
      "summary": "",
      "published": "2026-07-12T00:32:31.095890+00:00"
    },
    {
      "source": "Watson",
      "title": "Mutmasslicher Mord an Ann Widdecombe: Erneut Verdächtiger festgenommen",
      "url": "https://www.watson.ch/international/grossbritannien/304560987-mutmasslicher-mord-an-ann-widdecombe-erneut-verdaechtiger-festgenommen",
      "summary": "",
      "published": "2026-07-12T00:32:31.095890+00:00"
    },
    {
      "source": "Watson",
      "title": "Iran schliesst Strasse von Hormus – USA starten neue Angriffswelle",
      "url": "https://www.watson.ch/international/iran/295509659-iran-schliesst-strasse-von-hormus-usa-starten-neue-angriffswelle",
      "summary": "",
      "published": "2026-07-12T00:32:31.095890+00:00"
    },
    {
      "source": "Bote der Urschweiz",
      "title": "Bellingham schiesst die «Three Lions» in den Halbfinal",
      "url": "https://www.bote.ch/nachrichten/sport/bellingham-schiesst-england-gegen-norwegen-in-den-wm-halbfinal-art-1712414",
      "summary": "",
      "published": "2026-07-12T00:32:31.095890+00:00"
    },
    {
      "source": "Berner Zeitung",
      "title": "Schweiz-Spiel im Public Viewing: Schafft die Nati die Sensation? So fiebern Bernerinnen und Berner mit",
      "url": "https://www.bernerzeitung.ch/schweiz-argentinien-so-fiebern-bernerinnen-und-berner-mit-929112462775",
      "summary": "Wecker stellen oder direkt vom Ausgang zum Public Viewing: In Bern kommen mitten in der Nacht hunderte Leute zusammen, um den Viertelfinal-Knaller gegen Argentinien live mitzuverfolgen.",
      "published": "2026-07-12T01:02:35.880311+00:00"
    },
    {
      "source": "Zentralplus",
      "title": "GB: Neuer Verdächtiger festgenommen",
      "url": "https://www.zentralplus.ch/news/gb-neuer-verdaechtiger-festgenommen-2884360/",
      "summary": "Die Polizei hat im Fall der getöteten britischen Brexit-Politikerin Ann Widdecombe einen neuen Verdächtigen festgenommen. Dabei handelt es sich um einen 28-jährigen Briten. Die 78-jährige konservative",
      "published": "2026-07-12T01:02:35.880311+00:00"
    },
    {
      "source": "Watson",
      "title": "Schweiz – Argentinien live – der WM-Viertelfinal in Ticker und Stream",
      "url": "https://www.watson.ch/sport/liveticker/668192912-schweiz-argentinien-live-der-wm-viertelfinal-in-ticker-und-stream",
      "summary": "",
      "published": "2026-07-12T01:02:35.880311+00:00"
    },
    {
      "source": "Watson",
      "title": "England-Trainer Thomas Tuchel schnauzt Reporter an – und kritisiert Team",
      "url": "https://www.watson.ch/sport/fussball/845894770-england-trainer-thomas-tuchel-schnauzt-reporter-an-und-kritisiert-team",
      "summary": "",
      "published": "2026-07-12T01:02:35.880311+00:00"
    },
    {
      "source": "Freiburger Nachrichten",
      "title": "Jetzt live: Schafft die Schweiz im WM-Viertelfinal gegen Argentinien die Sensation?",
      "url": "https://www.freiburger-nachrichten.ch/story/276148/jetzt-live-schafft-die-schweiz-im-wmviertelfinal-gegen-argentinien-die-sensation",
      "summary": "",
      "published": "2026-07-12T01:02:35.880311+00:00"
    },
    {
      "source": "NZZ",
      "title": "LIVE-TICKER - Die Schweiz liegt im WM-Viertelfinal gegen Argentinien nach nur zehn Minuten bereits 0:1 in Rückstand",
      "url": "https://www.nzz.ch/sport/die-schweiz-liegt-im-wm-viertelfinal-gegen-argentinien-nach-nur-zehn-minuten-bereits-01-in-rueckstand-ld.10015046",
      "summary": "",
      "published": "2026-07-12T01:32:14.616277+00:00"
    },
    {
      "source": "Watson",
      "title": "Penatgon veröffentlicht neue UFO-Videos und UFO-Dokumente",
      "url": "https://www.watson.ch/wissen/international/726598644-penatgon-veroeffentlicht-neue-ufo-videos-und-ufo-dokumente",
      "summary": "",
      "published": "2026-07-12T01:32:14.616277+00:00"
    },
    {
      "source": "Freiburger Nachrichten",
      "title": "Bitter! Die Schweiz im Rückstand – das gibt uns Hoffnung",
      "url": "https://www.freiburger-nachrichten.ch/story/276148/bitter-die-schweiz-im-r%C3%BCckstand-das-gibt-uns-hoffnung",
      "summary": "",
      "published": "2026-07-12T01:32:14.616277+00:00"
    },
    {
      "source": "Bote der Urschweiz",
      "title": "Daumendrücken um drei Uhr nachts: So fiebert die Schweiz mit der Nati mit",
      "url": "https://www.bote.ch/nachrichten/schweizundwelt/fussball-wm-so-fiebert-die-schweiz-beim-viertelfinal-mit-art-1712415",
      "summary": "",
      "published": "2026-07-12T01:32:14.616277+00:00"
    },
    {
      "source": "Der Bund",
      "title": "Wer holt sich den Goldenen Schuh?: Das sind die besten Torschützen der Fussball-WM 2026",
      "url": "https://www.derbund.ch/wm-2026-mbappe-schliesst-mit-8-toren-zu-messi-auf-861898823534",
      "summary": "Der Torschützenkönig an einer WM wird mit dem Goldenen Schuh ausgezeichnet. Hier finden Sie die besten Scorer der WM-Endrunde.",
      "published": "2026-07-12T02:02:10.865936+00:00"
    },
    {
      "source": "Der Bund",
      "title": "Fussball-Weltmeisterschaft 2026: Der WM-Spielplan zum Downloaden und Ausdrucken",
      "url": "https://www.derbund.ch/fussball-wm-2026-spielplan-zum-downloaden-und-ausdrucken-7-576211289191",
      "summary": "Am 11. Juni 2026 beginnt die Fussball-WM in Kanada, Mexiko und den USA. Alle Partien und Spielorte auf einen Blick.",
      "published": "2026-07-12T02:02:10.865936+00:00"
    },
    {
      "source": "Basler Zeitung",
      "title": "Alle News zur WM: Südafrikanischer Nationalspieler Jayden Adams gestorben",
      "url": "https://www.bazonline.ch/fussball-wm-2026-suedafrikanischer-nationalspieler-jayden-adams-gestorben-885412667353",
      "summary": "Vom 11. Juni bis 19. Juli findet in den USA, Mexiko und Kanada die Fussball-WM statt. Alle wichtigen Informationen dazu finden Sie hier.",
      "published": "2026-07-12T02:02:10.865936+00:00"
    },
    {
      "source": "NZZ",
      "title": "LIVE-TICKER - Halbzeit in Kansas City: Die Schweiz liegt im WM-Viertelfinal gegen den Titelhalter Argentinien 0:1 in Rückstand",
      "url": "https://www.nzz.ch/sport/die-schweiz-liegt-im-wm-viertelfinal-gegen-argentinien-in-ruecklage-hat-den-fruehen-gegentreffer-aber-gut-verdaut-ld.10015046",
      "summary": "",
      "published": "2026-07-12T02:02:10.865936+00:00"
    },
    {
      "source": "Luzerner Zeitung",
      "title": "Artikel",
      "url": "https://www.luzernerzeitung.ch/bildergalerien/artikel-ld.4201582",
      "summary": "",
      "published": "2026-07-12T02:02:10.865936+00:00"
    },
    {
      "source": "Watson",
      "title": "Warum Bulgariens Radew der neue Orban werden könnte",
      "url": "https://www.watson.ch/international/analyse/145221671-warum-bulgariens-radew-der-neue-orban-werden-koennte",
      "summary": "",
      "published": "2026-07-12T02:02:10.865936+00:00"
    },
    {
      "source": "Watson",
      "title": "Neue Umfrage: AfD bleibt vorn – aber die Union holt auf",
      "url": "https://www.watson.ch/international/umfrage/338485000-neue-umfrage-afd-bleibt-vorn-aber-die-union-holt-auf",
      "summary": "",
      "published": "2026-07-12T02:02:10.865936+00:00"
    },
    {
      "source": "Freiburger Nachrichten",
      "title": "Erste Halbzeit ist vorbei: Die Schweiz liegt gegen Argentinien hinten",
      "url": "https://www.freiburger-nachrichten.ch/story/276148/erste-halbzeit-ist-vorbei-die-schweiz-liegt-gegen-argentinien-hinten",
      "summary": "",
      "published": "2026-07-12T02:02:10.865936+00:00"
    },
    {
      "source": "20 Minuten",
      "title": "«Das Tor hätte nicht zählen dürfen»: Engländer im Spidercam-Glück",
      "url": "https://www.20min.ch/story/wm-viertelfinal-das-tor-haette-nicht-zaehlen-duerfen-englaender-im-spidercam-glueck-103601497",
      "summary": "Beim WM-Viertelfinal zwischen England und Norwegen sorgte eine Szene vor dem Ausgleich für Diskussionen. Der Ball soll bei einem Abstoss ein Kamera-Kabel in der Luft touchiert haben.",
      "published": "2026-07-12T02:32:30.765118+00:00"
    },
    {
      "source": "Berner Zeitung",
      "title": "Alle News zur WM: Der Wirbel um Bellinghams erstes Tor",
      "url": "https://www.bernerzeitung.ch/fussball-wm-2026-suedafrikanischer-nationalspieler-jayden-adams-gestorben-885412667353",
      "summary": "Vom 11. Juni bis 19. Juli findet in den USA, Mexiko und Kanada die Fussball-WM statt. Alle wichtigen Informationen dazu finden Sie hier.",
      "published": "2026-07-12T02:32:30.765118+00:00"
    },
    {
      "source": "Schaffhauser Nachrichten",
      "title": "Ein Tag auf der Baustelle mit meinem Bruder: «Baggerfahren beruhigt die Nerven»",
      "url": "https://www.shn.ch/region/klettgau/2026-07-12/ein-tag-auf-der-baustelle-mit-meinem-bruder-baggerfahren-beruhigt-die",
      "summary": "Drei Dinge wollte ich an diesem Tag herausfinden: Was mögen die Bauarbeiter eigentlich lieber, Hitze oder Kälte? Wo kann ich selber mitarbeiten? Und was hat sich in den letzten 40 Jahren auf dem Bau v",
      "published": "2026-07-12T02:32:30.765118+00:00"
    },
    {
      "source": "Schaffhauser Nachrichten",
      "title": "FIFA: Die Realität schlägt jede Verschwörungstheorie",
      "url": "https://www.shn.ch/forum-meinung/kolumnen/2026-07-12/fifa-die-realitaet-schlaegt-jede-verschwoerungstheorie",
      "summary": "Es braucht gar keine Theorien über versteckte Hinterzimmerdeals und Bestechungszahlungen: Der Weltfussballverband reagiert schon auf Druck per Telefonanruf. Und doch hat Trumps und Infantinos Vorgehen",
      "published": "2026-07-12T02:32:30.765118+00:00"
    },
    {
      "source": "Luzerner Zeitung",
      "title": "Die Bilder zum Wm Viertelfinal Zwischen der Schweiz und Argentinien",
      "url": "https://www.luzernerzeitung.ch/bildergalerien/die-bilder-zum-wm-viertelfinal-zwischen-der-schweiz-und-argentinien-ld.4201583",
      "summary": "",
      "published": "2026-07-12T02:32:30.765118+00:00"
    },
    {
      "source": "Watson",
      "title": "WM: Was bei der Schweizer Nati beim Argentinien-Tor schiefgelaufen ist",
      "url": "https://www.watson.ch/sport/fussball/427775484-wm-was-bei-der-schweizer-nati-beim-argentinien-tor-schiefgelaufen-ist",
      "summary": "",
      "published": "2026-07-12T02:32:30.765118+00:00"
    },
    {
      "source": "Watson",
      "title": "Berichte: Oman mit Vorschlag für gebührenfreie Schifffahrt",
      "url": "https://www.watson.ch/international/iran/492464527-berichte-oman-mit-vorschlag-fuer-gebuehrenfreie-schifffahrt",
      "summary": "",
      "published": "2026-07-12T02:32:30.765118+00:00"
    },
    {
      "source": "Freiburger Nachrichten",
      "title": "Die Zeit rennt der Nati davon: Findet sie einen Weg gegen Messi und Co.?",
      "url": "https://www.freiburger-nachrichten.ch/story/276148/die-zeit-rennt-der-nati-davon-findet-sie-einen-weg-gegen-messi-und-co",
      "summary": "",
      "published": "2026-07-12T02:32:30.765118+00:00"
    },
    {
      "source": "Tages-Anzeiger",
      "title": "Brustkrebs und Sport: Krebsbetroffene Frauen finden auf dem Zürichsee neue Kraft beim Rudern",
      "url": "https://www.tagesanzeiger.ch/brustkrebs-rudern-auf-dem-zuerichsee-als-therapie-370045701930",
      "summary": "Die Ruderwoche «ramer en rose» bringt brustkrebsbetroffene Frauen aufs Wasser – manche nur drei Tage nach der Operation. Ein Onkologe erklärt, weshalb Bewegung wichtig ist.",
      "published": "2026-07-12T03:02:38.179577+00:00"
    },
    {
      "source": "Zentralplus",
      "title": "CAN: Tote bei Schüssen in Toronto",
      "url": "https://www.zentralplus.ch/news/can-tote-bei-schuessen-in-toronto-2884362/",
      "summary": "Zwei Menschen sind in der Nähe eines Strassenfests in der kanadischen Millionenstadt Toronto durch Schüsse getötet worden. Mehrere weitere Personen wurden laut Polizei angeschossen. Über die Hintergrü",
      "published": "2026-07-12T03:02:38.179577+00:00"
    },
    {
      "source": "Südostschweiz",
      "title": "Sonntagsquiz Nen Denkt Sich Da Noch was aus",
      "url": "https://www.suedostschweiz.ch/graubuenden/sonntagsquiz-nen-denkt-sich-da-noch-was-aus-1951548",
      "summary": "",
      "published": "2026-07-12T03:02:38.179577+00:00"
    },
    {
      "source": "Südostschweiz",
      "title": "Ärger über Gummiflamingos das Sind die Witzigsten Google Bewertungen aus Graubünden",
      "url": "https://www.suedostschweiz.ch/graubuenden/aerger-ueber-gummiflamingos-das-sind-die-witzigsten-google-bewertungen-aus-graubuenden-1976366",
      "summary": "",
      "published": "2026-07-12T03:02:38.179577+00:00"
    },
    {
      "source": "Südostschweiz",
      "title": "Hauptstrasse in Netstal Bundesamt Is Watching You",
      "url": "https://www.suedostschweiz.ch/glarus/hauptstrasse-in-netstal-bundesamt-is-watching-you-1952145",
      "summary": "",
      "published": "2026-07-12T03:02:38.179577+00:00"
    },
    {
      "source": "Luzerner Zeitung",
      "title": "Hitze in Luzern Kartonhaufen Zeigen Hohen Kühlbedarf",
      "url": "https://www.luzernerzeitung.ch/zentralschweiz/stadt-region-luzern/hitze-in-luzern-kartonhaufen-zeigen-hohen-kuehlbedarf-ld.4200645",
      "summary": "",
      "published": "2026-07-12T03:02:38.179577+00:00"
    },
    {
      "source": "St. Galler Tagblatt",
      "title": "Wie Grillgemüse Überrascht",
      "url": "https://www.tagblatt.ch/ostschweiz/ressort-ostschweiz/wie-grillgemuese-ueberrascht-ld.4201496",
      "summary": "",
      "published": "2026-07-12T03:02:38.179577+00:00"
    },
    {
      "source": "bz Basel",
      "title": "Feuerwerk am 1 August Behörden Prüfen Verbot Wegen Trockenheit",
      "url": "https://www.bzbasel.ch/basel/baselland/feuerwerk-am-1-august-behoerden-pruefen-verbot-wegen-trockenheit-ld.4200262",
      "summary": "",
      "published": "2026-07-12T03:02:38.179577+00:00"
    },
    {
      "source": "bz Basel",
      "title": "Ende eines Mythos Jetzt Wird der Dreispitz Neu Verhandelt",
      "url": "https://www.bzbasel.ch/basel/baselland/ende-eines-mythos-jetzt-wird-der-dreispitz-neu-verhandelt-ld.4195217",
      "summary": "",
      "published": "2026-07-12T03:02:38.179577+00:00"
    },
    {
      "source": "bz Basel",
      "title": "Basler Staatsarchiv Zieht Ab Oktober 2027 um",
      "url": "https://www.bzbasel.ch/basel/basel-stadt/basler-staatsarchiv-zieht-ab-oktober-2027-um-ld.4200340",
      "summary": "",
      "published": "2026-07-12T03:02:38.179577+00:00"
    },
    {
      "source": "Zuger Zeitung",
      "title": "Pumpfoiling auf dem Zugersee Unser Reporter Testet den Trendsport",
      "url": "https://www.zugerzeitung.ch/zentralschweiz/zug/pumpfoiling-auf-dem-zugersee-unser-reporter-testet-den-trendsport-ld.4199225",
      "summary": "",
      "published": "2026-07-12T03:02:38.179577+00:00"
    },
    {
      "source": "Watson",
      "title": "WM 2026: Weshalb Embolo gegen Argentinien nicht hätte Rot sehen dürfen",
      "url": "https://www.watson.ch/sport/fussball/370759075-wm-2026-weshalb-embolo-gegen-argentinien-nicht-haette-rot-sehen-duerfen",
      "summary": "",
      "published": "2026-07-12T03:02:38.179577+00:00"
    },
    {
      "source": "Watson",
      "title": "Zwei Tote nach Schiesserei in Toronto – Fahndung läuft",
      "url": "https://www.watson.ch/international/verbrechen/435872378-zwei-tote-nach-schiesserei-in-toronto-fahndung-laeuft",
      "summary": "",
      "published": "2026-07-12T03:02:38.179577+00:00"
    },
    {
      "source": "Watson",
      "title": "History Porn Teil CXII: Geschichte in 39 Wahnsinns-Bildern",
      "url": "https://www.watson.ch/wissen/history-porn/372477272-history-porn-teil-cxii-geschichte-in-39-wahnsinns-bildern",
      "summary": "",
      "published": "2026-07-12T03:02:38.179577+00:00"
    },
    {
      "source": "Freiburger Nachrichten",
      "title": "Steinway: Der Rolls Royce unter den Klavieren",
      "url": "https://www.freiburger-nachrichten.ch/story/276131/steinway-der-rolls-royce-unter-den-klavieren",
      "summary": "",
      "published": "2026-07-12T03:02:38.179577+00:00"
    },
    {
      "source": "Freiburger Nachrichten",
      "title": "Gibt es Typen wie «Rain Man» im echten Leben?",
      "url": "https://www.freiburger-nachrichten.ch/story/276071/gibt-es-typen-wie-rain-man-im-echten-leben",
      "summary": "",
      "published": "2026-07-12T03:02:38.179577+00:00"
    },
    {
      "source": "Freiburger Nachrichten",
      "title": "Diese Reaktionen löste die «Schulinspektion»-Kolumne aus",
      "url": "https://www.freiburger-nachrichten.ch/story/276074/diese-reaktionen-l%C3%B6ste-die-schulinspektionkolumne-aus",
      "summary": "",
      "published": "2026-07-12T03:02:38.179577+00:00"
    },
    {
      "source": "Freiburger Nachrichten",
      "title": "Die Odyssee: Das grosse Quiz zum Kinostart der neuen Verfilmung",
      "url": "https://www.freiburger-nachrichten.ch/story/276070/die-odyssee-das-grosse-quiz-zum-kinostart-der-neuen-verfilmung",
      "summary": "",
      "published": "2026-07-12T03:02:38.179577+00:00"
    },
    {
      "source": "Freiburger Nachrichten",
      "title": "Der Test: Ich habe den BH nach Mass ausprobiert – das ist mein Urteil",
      "url": "https://www.freiburger-nachrichten.ch/story/276080/der-test-ich-habe-den-bh-nach-mass-ausprobiert%C2%A0-das-ist-mein-urteil",
      "summary": "",
      "published": "2026-07-12T03:02:38.179577+00:00"
    },
    {
      "source": "Freiburger Nachrichten",
      "title": "Gemeinsam den Wäscheberg bewältigen und dabei die Vergangenheit aufleben lassen",
      "url": "https://www.freiburger-nachrichten.ch/story/274970/gemeinsam-den-w%C3%A4scheberg-bew%C3%A4ltigen-und-dabei-die-vergangenheit-aufleben-lassen",
      "summary": "",
      "published": "2026-07-12T03:02:38.179577+00:00"
    },
    {
      "source": "Freiburger Nachrichten",
      "title": "Kurz nach dem Ausgleich: Embolo fliegt wegen einer unnötigen Schwalbe vom Platz!",
      "url": "https://www.freiburger-nachrichten.ch/story/276148/kurz-nach-dem-ausgleich-embolo-fliegt-wegen-einer-unn%C3%B6tigen-schwalbe-vom-platz",
      "summary": "",
      "published": "2026-07-12T03:02:38.179577+00:00"
    },
    {
      "source": "Bote der Urschweiz",
      "title": "Schwerelos über den Zugersee: Unser Reporter testet den Trendsport Pumpfoiling",
      "url": "https://www.bote.ch/nachrichten/zentralschweiz/pumpfoiling-auf-dem-zugersee-unser-reporter-testet-den-trendsport-art-1712416",
      "summary": "",
      "published": "2026-07-12T03:02:38.179577+00:00"
    },
    {
      "source": "Blick",
      "title": "Editorial über Temperaturen und Umweltpolitik: Die unheimlich unpolitische Hitze",
      "url": "https://www.blick.ch/meinung/editorial-ueber-die-unheimlich-unpolitische-hitze-kartoffelstock-auf-alten-meistern-id22102652.html",
      "summary": "Je heisser der Sommer, desto cooler die Klimadebatte. Wie konnte aus einem politischen Aufregerthema eine Randnotiz werden?",
      "published": "2026-07-12T03:32:29.996549+00:00"
    },
    {
      "source": "20 Minuten",
      "title": "Darum flog Embolo wegen Schwalbe nach VAR-Eingriff vom Platz",
      "url": "https://www.20min.ch/story/neue-regel-darum-flog-embolo-wegen-schwalbe-nach-var-eingriff-vom-platz-103601574",
      "summary": "Breel Embolo sieht im WM-Viertelfinal gegen Argentinien korrekterweise die Rote Karte aufgrund einer Schwalbe und einer neuen Regel.",
      "published": "2026-07-12T03:32:29.996549+00:00"
    },
    {
      "source": "20 Minuten",
      "title": "Christian Wolf schlägt Rivella-Sirup vor: Fans sind begeistert",
      "url": "https://www.20min.ch/story/more-nutrition-christian-wolf-schlaegt-rivella-sirup-vor-fans-sind-begeistert-103600992",
      "summary": "More-Nutrition-Mitgründer Christian Wolf will wissen, ob die Schweiz einen zuckerfreien Sirup mit Rivella-Geschmack will. Die Reaktionen sind fast nur positiv.",
      "published": "2026-07-12T03:32:29.996549+00:00"
    },
    {
      "source": "Zentralplus",
      "title": "Zug verbockt Transparenzgesetz – sagen die Initianten",
      "url": "https://www.zentralplus.ch/politik/zug-verbockt-transparenzgesetz-sagen-die-initianten-2883773/",
      "summary": "Das Zuger Stimmvolk sagte Ja zu mehr Transparenz. Nun legt die Regierung das Gesetz vor. Mitinitiator Konradin Franzini sieht hohe Hürden, eine verwässerte Umsetzung – und bringt bereits das Referendu",
      "published": "2026-07-12T03:32:29.996549+00:00"
    },
    {
      "source": "NZZ",
      "title": "LIVE-TICKER - Breel Embolo fliegt vom Platz – 15 Minuten trennen die Schweiz im WM-Viertelfinal gegen Argentinien noch vom Penaltyschiessen",
      "url": "https://www.nzz.ch/sport/breel-embolo-fliegt-vom-platz-15-minuten-trennen-die-schweiz-im-wm-viertelfinal-gegen-argentinien-noch-vom-penaltyschiessen-ld.10015046",
      "summary": "",
      "published": "2026-07-12T03:32:29.996549+00:00"
    },
    {
      "source": "NZZ",
      "title": "Zürich ist teuer, lebenswert, voller Stau und kulturell verkümmert: wie die Stadt in der seltsamen Welt der internationalen Rankings abschneidet",
      "url": "https://www.nzz.ch/zuerich/zuerich-die-ranking-stadt-von-lebensqualitaet-bis-reichtum-immer-zuoberst-ld.10014623",
      "summary": "",
      "published": "2026-07-12T03:32:29.996549+00:00"
    },
    {
      "source": "Watson",
      "title": "Die Drohnenthematik dominiert die News – die Sonntagspresse",
      "url": "https://www.watson.ch/schweiz/ahv/158885472-die-drohnenthematik-dominiert-die-news-die-sonntagspresse",
      "summary": "",
      "published": "2026-07-12T03:32:29.996549+00:00"
    },
    {
      "source": "Freiburger Nachrichten",
      "title": "Pause in der Verlängerung – Schweiz darf trotz Unterzahl weiter vom Halbfinal träumen",
      "url": "https://www.freiburger-nachrichten.ch/story/276148/pause-in-der-verl%C3%A4ngerung-schweiz-darf-trotz-unterzahl-weiter-vom-halbfinal-tr%C3%A4umen",
      "summary": "",
      "published": "2026-07-12T03:32:29.996549+00:00"
    },
    {
      "source": "Tages-Anzeiger",
      "title": "Die Lesernoten: Wie bewerten Sie die Schweizer nach dem Viertelfinal-Aus?",
      "url": "https://www.tagesanzeiger.ch/wm-2026-lesernoten-der-schweiz-zum-viertelfinal-gegen-argentinien-356483023539",
      "summary": "Es sollte nicht sein. Stimmen Sie ab, wer ihnen trotz der Niederlage nach Verlängerung gegen Argentinien gefallen hat oder nicht.",
      "published": "2026-07-12T04:02:13.279782+00:00"
    },
    {
      "source": "Tages-Anzeiger",
      "title": "Sweet Home: 10 Tipps für das Feriengefühl daheim",
      "url": "https://www.tagesanzeiger.ch/sommerferien-10-tipps-fuer-ferienstimmung-zu-hause-122937839616",
      "summary": "Gehören Sie nicht zu denen, die bereits abgereist sind oder gerade ihre Koffer packen? Kein Problem, Feriengefühl lässt sich auch in den Alltag und ins Zuhause zaubern.",
      "published": "2026-07-12T04:02:13.279782+00:00"
    },
    {
      "source": "Der Bund",
      "title": "Schweiz-Spiel im Public Viewing: Tristesse statt Triumph: So haben Bernerinnen und Berner mitgelitten",
      "url": "https://www.derbund.ch/schweiz-argentinien-so-fiebern-bernerinnen-und-berner-mit-929112462775",
      "summary": "In Bern kamen mitten in der Nacht hunderte Leute zusammen, um den Viertelfinal-Knaller gegen Argentinien live mitzuverfolgen. Die aufkommende Party endete abrupt.",
      "published": "2026-07-12T04:02:13.279782+00:00"
    },
    {
      "source": "NZZ",
      "title": "LIVE-TICKER - Die Schweiz verliert den WM-Viertelfinal gegen Argentinien nach heroischem Kampf in Unterzahl mit 1:3 – mit seinem Platzverweis erweist Breel Embolo dem Team einen Bärendienst",
      "url": "https://www.nzz.ch/sport/die-schweiz-verliert-den-wm-viertelfinal-gegen-argentinien-nach-heroischem-kampf-in-unterzahl-mit-13-mit-seinem-platzverweis-erweist-breel-embolo-dem-team-einen-baerendienst-ld.10015046",
      "summary": "",
      "published": "2026-07-12T04:02:13.279782+00:00"
    },
    {
      "source": "NZZ",
      "title": "Wie Deutschland reich wurde, eine schöne Betrügerin und ein «schwarzer Mozart»: Die Kulturtipps der «NZZ am Sonntag»",
      "url": "https://www.nzz.ch/feuilleton/wie-deutschland-reich-wurde-eine-schoene-betruegerin-und-ein-schwarzer-mozart-die-kulturtipps-der-nzz-am-sonntag-ld.10014470",
      "summary": "",
      "published": "2026-07-12T04:02:13.279782+00:00"
    },
    {
      "source": "NZZ",
      "title": "Mein Strohhut treibt Schabernack mit mir",
      "url": "https://www.nzz.ch/feuilleton/mein-strohhut-treibt-schabernack-mit-mir-ld.10014460",
      "summary": "",
      "published": "2026-07-12T04:02:13.279782+00:00"
    },
    {
      "source": "NZZ",
      "title": "Das Regime in Teheran und Tausende Anhänger drohen Donald Trump mit der Ermordung – muss sich der US-Präsident nun wirklich fürchten?",
      "url": "https://www.nzz.ch/international/das-regime-in-teheran-und-tausende-anhaenger-drohen-donald-trump-mit-der-ermordung-muss-sich-der-us-praesident-nun-wirklich-fuerchten-ld.10015072",
      "summary": "",
      "published": "2026-07-12T04:02:13.279782+00:00"
    },
    {
      "source": "NZZ",
      "title": "KOMMENTAR - Die Bürgerlichen dürfen den Klimaschutz nicht den Grünen überlassen",
      "url": "https://www.nzz.ch/meinung/die-buergerlichen-duerfen-den-klimaschutz-nicht-den-gruenen-ueberlassen-ld.10014962",
      "summary": "",
      "published": "2026-07-12T04:02:13.279782+00:00"
    },
    {
      "source": "NZZ",
      "title": "Sein letztes Gefecht: Volkswagen-Konzernchef Oliver Blume geht aufs Ganze",
      "url": "https://www.nzz.ch/wirtschaft/sein-letztes-gefecht-volkswagen-konzernchef-oliver-blume-geht-aus-ganze-ld.10014952",
      "summary": "",
      "published": "2026-07-12T04:02:13.279782+00:00"
    },
    {
      "source": "NZZ",
      "title": "Im Namen von Samaria: Israel missbraucht archäologische Parks, um Palästinenser zu enteignen",
      "url": "https://www.nzz.ch/international/im-namen-von-samaria-israel-missbraucht-archaeologische-parks-um-palaestinenser-zu-enteignen-ld.10014923",
      "summary": "",
      "published": "2026-07-12T04:02:13.279782+00:00"
    },
    {
      "source": "NZZ",
      "title": "Wie Didier Deschamps das Meisterwerk seiner Ära geschaffen hat",
      "url": "https://www.nzz.ch/sport/wm-2026-wie-frankreich-coach-deschamps-sein-team-zum-erfolg-fuehrt-ld.10014901",
      "summary": "",
      "published": "2026-07-12T04:02:13.279782+00:00"
    },
    {
      "source": "NZZ",
      "title": "«Was mich nicht umbringt, macht mich stärker»: Schön wär’s",
      "url": "https://www.nzz.ch/wissenschaft/was-mich-nicht-umbringt-die-wahrheit-hinter-dem-posttraumatischen-wachstum-ld.10014882",
      "summary": "",
      "published": "2026-07-12T04:02:13.279782+00:00"
    },
    {
      "source": "NZZ",
      "title": "INTERVIEW - Kann Marine Le Pen jetzt noch gestoppt werden? Vielleicht. Ein Mann könnte sich ihr in den Weg stellen, sagt der französische Politologe Luc Rouban",
      "url": "https://www.nzz.ch/international/kann-marine-le-pen-jetzt-noch-gestoppt-werden-vielleicht-ein-mann-koennte-sich-ihr-in-den-weg-stellen-sagt-der-franzoesische-politologe-luc-rouban-ld.10014807",
      "summary": "",
      "published": "2026-07-12T04:02:13.279782+00:00"
    },
    {
      "source": "NZZ",
      "title": "Donald Trump versprach Amerikas Bauern ein «goldenes Zeitalter». Auf dem Hof der Familie Bardole in Iowa ist das Gegenteil eingetreten",
      "url": "https://www.nzz.ch/international/donald-trump-versprach-amerikas-bauern-ein-goldenes-zeitalter-auf-dem-hof-der-familie-bardole-in-iowa-ist-das-gegenteil-eingetreten-ld.10014806",
      "summary": "",
      "published": "2026-07-12T04:02:13.279782+00:00"
    },
    {
      "source": "NZZ",
      "title": "Die Warteschlangen fürs Brot führten zum Ende des russischen Zarenreichs. Und die heutigen Warteschlangen fürs Benzin? Wohin führen sie?",
      "url": "https://www.nzz.ch/international/die-warteschlangen-fuers-brot-fuehrten-zum-ende-des-russischen-zarenreichs-und-die-heutigen-warteschlangen-fuers-benzin-wohin-fuehren-sie-ld.10014804",
      "summary": "",
      "published": "2026-07-12T04:02:13.279782+00:00"
    },
    {
      "source": "NZZ",
      "title": "Darüber spricht Madrid: heiss, heisser, so geht’s nicht weiter",
      "url": "https://www.nzz.ch/international/darueber-spricht-madrid-heiss-heisser-so-geht-s-nicht-weiter-ld.10014801",
      "summary": "",
      "published": "2026-07-12T04:02:13.279782+00:00"
    },
    {
      "source": "NZZ",
      "title": "Erstmals in ihrer Geschichte als börsenkotierte Firma fällt die Swisscom aus dem Leitindex SMI",
      "url": "https://www.nzz.ch/wirtschaft/erstmals-in-ihrer-geschichte-als-boersenkotierte-firma-faellt-die-swisscom-aus-dem-leitindex-smi-ld.10014795",
      "summary": "",
      "published": "2026-07-12T04:02:13.279782+00:00"
    },
    {
      "source": "NZZ",
      "title": "Endlich Sommerferien – füllen wir sie nicht mit Aktivitäten und Strebsamkeit",
      "url": "https://www.nzz.ch/wirtschaft/endlich-sommerferien-fuellen-wir-sie-nicht-mit-aktivitaeten-und-strebsamkeit-ld.10014794",
      "summary": "",
      "published": "2026-07-12T04:02:13.279782+00:00"
    },
    {
      "source": "Watson",
      "title": "Aus der Traum: Schweiz scheitert gegen Argentinien nach kontroversem Rot",
      "url": "https://www.watson.ch/sport/liveticker/668192912-aus-der-traum-schweiz-scheitert-gegen-argentinien-nach-kontroversem-rot",
      "summary": "",
      "published": "2026-07-12T04:02:13.279782+00:00"
    },
    {
      "source": "Watson",
      "title": "Konferenz einer rechtsextremen Gruppe in Waadt kurzfristig abgesagt",
      "url": "https://www.watson.ch/schweiz/ahv/158885472-konferenz-einer-rechtsextremen-gruppe-in-waadt-kurzfristig-abgesagt",
      "summary": "",
      "published": "2026-07-12T04:02:13.279782+00:00"
    },
    {
      "source": "Freiburger Nachrichten",
      "title": "Bitter! Schweiz verliert den WM-Viertelfinal gegen Argentinien nach umstrittener Roter Karte",
      "url": "https://www.freiburger-nachrichten.ch/story/276148/bitter-schweiz-verliert-den-wmviertelfinal-gegen-argentinien-nach-umstrittener-roter-karte",
      "summary": "",
      "published": "2026-07-12T04:02:13.279782+00:00"
    },
    {
      "source": "Bote der Urschweiz",
      "title": "Spiel verpasst? Hier gibt's die wichtigsten Szenen vom Schweizer Viertelfinal gegen Argentinien",
      "url": "https://www.bote.ch/nachrichten/sport/schweiz-argentinien-die-highlights-vom-wm-viertelfinal-im-video-art-1712417",
      "summary": "",
      "published": "2026-07-12T04:02:13.279782+00:00"
    },
    {
      "source": "20 Minuten",
      "title": "«Es fühlt sich unfair an»: Nati-Stars nach WM-Out enttäuscht",
      "url": "https://www.20min.ch/story/gegen-argentinien-es-fuehlt-sich-unfair-an-nati-stars-nach-wm-out-enttaeuscht-103601674",
      "summary": "Die Nati verliert den WM-Viertelfinal gegen Argentinien. Das sind die ersten Reaktionen.",
      "published": "2026-07-12T04:32:37.845547+00:00"
    },
    {
      "source": "20 Minuten",
      "title": "Tor der WM? Hier trifft Julián Álvarez mitten ins Schweizer Herz",
      "url": "https://www.20min.ch/video/gauchos-versenkt-die-nati-tor-der-wm-hier-trifft-julian-alvarez-mitten-ins-schweizer-herz-103601676",
      "summary": "Julián Álvarez war es, der in der 112. Minute mit einem absolut fantastischen Tor das 2:1 für Argentinien in der Verlängerung schoss. Am Ende siegen die Südamerikaner mit 3:1 – gleichbedeutend mit dem",
      "published": "2026-07-12T04:32:37.845547+00:00"
    },
    {
      "source": "Tages-Anzeiger",
      "title": "Die Schweizer WM: Trotz allem: geniessen, festhalten, abspeichern – und den Schweizer Weg weiter verfolgen",
      "url": "https://www.tagesanzeiger.ch/wm-viertelfinal-yakin-muss-schweizer-nationalteam-erneuern-541332227576",
      "summary": "Das Aus im Viertelfinal schmerzt. Der Erfolg bei dieser WM kann der Schweiz aber als Anreiz dienen, um in Zukunft von noch Grösserem zu träumen. Auch wenn das Team vor einem Umbruch steht.",
      "published": "2026-07-12T04:32:37.845547+00:00"
    },
    {
      "source": "Tages-Anzeiger",
      "title": "Leck bei der AHV: 40 Millionen Franken zu viel ins Ausland bezahlt: Die schwierige Jagd nach Renten­geldern",
      "url": "https://www.tagesanzeiger.ch/ahv-fast-40-millionen-franken-zu-viel-ins-ausland-gezahlt-731237774549",
      "summary": "Werden Todesfälle oder Wegzüge verheimlicht, zahlt die AHV manchmal jahre­lang unbemerkt weiter. Ein neuer Bericht der Finanz­kontrolle zeigt, warum die Eintreibung des Geldes harzt – und wieso der Bu",
      "published": "2026-07-12T04:32:37.845547+00:00"
    },
    {
      "source": "Tages-Anzeiger",
      "title": "Streit um Hundezonen: Hündeler verteidigen die Zürcher Allmend: «Wir geben keinen Quadratmeter her!»",
      "url": "https://www.tagesanzeiger.ch/zuerich-allmend-stadt-plant-hundefreie-zone-ab-2027-345109556403",
      "summary": "Ausgerechnet im Hundeparadies möchte die Stadt Zürich eine hundefreie Zone einrichten. Die Hundehaltenden kündigen Widerstand an.",
      "published": "2026-07-12T04:32:37.845547+00:00"
    },
    {
      "source": "Tages-Anzeiger",
      "title": "Schweiz-Argentinien: Dieser Sonntag ist kein Feiertag: Fans in Winterthur wachen und bangen vergebens",
      "url": "https://www.tagesanzeiger.ch/schweiz-argentinien-dieser-sonntag-ist-kein-feiertag-fans-in-winterthur-wachen-und-bangen-vergebens-904762679810",
      "summary": "Die lange Nacht in den Public Viewings in Winterthur endete mit einer Niederlage. Kurz vor 6 Uhr morgens gewinnt Argentinien gegen die Schweiz mit 3:1.",
      "published": "2026-07-12T04:32:37.845547+00:00"
    },
    {
      "source": "Basler Zeitung",
      "title": "Gastronomie in der Hitzewelle: «50 Grad Innentemperatur sind kein Arbeitsklima, das wir unseren Leuten zumuten wollen»",
      "url": "https://www.bazonline.ch/hitze-in-basel-restaurants-schliessen-bei-50-grad-die-kueche-118828922234",
      "summary": "Basler Gastrobetriebe ringen mit teilweise extremen Bedingungen in ihren Küchen – und finden höchst unterschiedliche Lösungen.",
      "published": "2026-07-12T04:32:37.845547+00:00"
    },
    {
      "source": "NZZ",
      "title": "Der Platzverweis gegen Embolo wiegt zu schwer: Die Schweizer Fussballer verlieren den WM-Viertelfinal gegen Argentinien 1:3",
      "url": "https://www.nzz.ch/sport/fussball/der-platzverweis-gegen-embolo-wiegt-zu-schwer-die-schweizer-fussballer-verlieren-den-wm-viertelfinal-gegen-argentinien-13-ld.10015045",
      "summary": "",
      "published": "2026-07-12T04:32:37.845547+00:00"
    },
    {
      "source": "Südostschweiz",
      "title": "Jubeln Zittern Haareraufen So Fiebern die Fans im Grössten Bündner Public Viewing mit",
      "url": "https://www.suedostschweiz.ch/regionalsport/jubeln-zittern-haareraufen-so-fiebern-die-fans-im-groessten-buendner-public-viewing-mit-2086647",
      "summary": "",
      "published": "2026-07-12T04:32:37.845547+00:00"
    },
    {
      "source": "Watson",
      "title": "Crew verlässt Schiff in Strasse von Hormus – Brand an Bord",
      "url": "https://www.watson.ch/international/iran/820437372-crew-verlaesst-schiff-in-strasse-von-hormus-brand-an-bord",
      "summary": "",
      "published": "2026-07-12T04:32:37.845547+00:00"
    },
    {
      "source": "20 Minuten",
      "title": "Aargau wird zum Hub des Kokainhandels",
      "url": "https://www.20min.ch/story/drogen-kokain-konsum-aargau-als-verteilknoten-drogenfahnder-103601551",
      "summary": "Der Kokain-Konsum in der Schweiz nimmt zu - das ist bekannt. Dabei fungiert der Kanton Aargau laut einem Medienbericht als Verteilknoten des Kokainhandel.",
      "published": "2026-07-12T05:02:13.232693+00:00"
    },
    {
      "source": "Tages-Anzeiger",
      "title": "Stimmen zur Viertelfinal-Niederlage: «Es ist schwierig, wenn man auch den Schiedsrichter gegen sich hat»",
      "url": "https://www.tagesanzeiger.ch/fussball-wm-die-stimmen-der-natispieler-nach-dem-viertelfinal-gegen-argentinien-887057552309",
      "summary": "Nach bitteren Out in der Verlängerung gegen Weltmeister Argentinien suchen die Schweizer Erklärungen. Manuel Akanji sieht auch im Schiedsrichter einen Verantwortlichen.",
      "published": "2026-07-12T05:02:13.232693+00:00"
    },
    {
      "source": "Watson",
      "title": "Oh Embolo, oh Embolo … Kommentar zum Schweizer WM-Aus gegen Argentinien",
      "url": "https://www.watson.ch/sport/kommentar/664731272-oh-embolo-oh-embolo-kommentar-zum-schweizer-wm-aus-gegen-argentinien",
      "summary": "",
      "published": "2026-07-12T05:02:13.232693+00:00"
    },
    {
      "source": "Watson",
      "title": "Liveticker Nahost: Irans Revolutionsgarden haben US-Basen angegriffen",
      "url": "https://www.watson.ch/international/liveticker/295509659-liveticker-nahost-irans-revolutionsgarden-haben-us-basen-angegriffen",
      "summary": "",
      "published": "2026-07-12T05:02:13.232693+00:00"
    },
    {
      "source": "Freiburger Nachrichten",
      "title": "Der neue Business-Zweig der Bauern floriert: Care Farming",
      "url": "https://www.freiburger-nachrichten.ch/story/276077/der-neue-businesszweig-der-bauern-floriert-care-farming",
      "summary": "",
      "published": "2026-07-12T05:02:13.232693+00:00"
    },
    {
      "source": "Freiburger Nachrichten",
      "title": "Der Drache aus dem Galterntal",
      "url": "https://www.freiburger-nachrichten.ch/story/272248/der-drache-aus-dem-galterntal",
      "summary": "",
      "published": "2026-07-12T05:02:13.232693+00:00"
    },
    {
      "source": "Freiburger Nachrichten",
      "title": "1:3 – Schweiz verliert den WM-Viertelfinal gegen Argentinien nach umstrittener Roter Karte",
      "url": "https://www.freiburger-nachrichten.ch/story/276148/13-schweiz-verliert-den-wmviertelfinal-gegen-argentinien-nach-umstrittener-roter-karte",
      "summary": "",
      "published": "2026-07-12T05:02:13.232693+00:00"
    },
    {
      "source": "Bote der Urschweiz",
      "title": "Nach bitterem Out gegen Argentinien: Bewerten Sie die Leistungen der Nati",
      "url": "https://www.bote.ch/nachrichten/sport/schweiz-gegen-argentinien-spielerleistungen-bewerten-art-1712419",
      "summary": "",
      "published": "2026-07-12T05:02:13.232693+00:00"
    },
    {
      "source": "Bote der Urschweiz",
      "title": "Hinten top, ganz vorne flop: Im Verbund haben sie Messi im Griff – doch einer macht die Rechnung ohne den VAR",
      "url": "https://www.bote.ch/nachrichten/sport/noten-der-schweizer-nati-im-wm-viertelfinal-gegen-argentinien-art-1712418",
      "summary": "",
      "published": "2026-07-12T05:02:13.232693+00:00"
    },
    {
      "source": "Inside Paradeplatz",
      "title": "Die Schweiz Trieb Weltmeister Argentinien Ans Limit",
      "url": "https://insideparadeplatz.ch/2026/07/12/die-schweiz-trieb-weltmeister-argentinien-ans-limit/",
      "summary": "",
      "published": "2026-07-12T05:02:13.232693+00:00"
    }
  ]
}