{
  "https://www.blick.ch/news/rss.xml": {
    "last_modified": "Fri, 24 Jul 2026 08:25:19 GMT",
    "etag": "\"771bb9382afc7bdb8ecc80c5e88ada76\""
  },
  "https://partner-feeds.20min.ch/rss/20minuten": {
    "etag": "W/\"17ebe-49/Y3zfmK4JHu1oQ9gWR3xjyofw\""
  },
  "https://partner-feeds.publishing.tamedia.ch/rss/tagesanzeiger/": {
    "etag": "W/\"f7bb-y9AnCuF8bgAQNOzmNnPEEkhyNls\""
  },
  "https://partner-feeds.publishing.tamedia.ch/rss/bernerzeitung/": {
    "etag": "W/\"f4fb-tnpjur6N2ErX7+gpmJSdayyqTco\""
  },
  "https://www.zentralplus.ch/feed/": {
    "last_modified": "Fri, 24 Jul 2026 08:25:13 GMT"
  },
  "https://www.finews.ch/news?format=feed": {
    "last_modified": "Fri, 24 Jul 2026 08:30:42 GMT"
  },
  "https://www.netzwoche.ch/rss.xml": {
    "last_modified": "Fri, 24 Jul 2026 07:05:32 GMT",
    "etag": "\"1784876732\""
  },
  "https://www.nzz.ch/recent.rss": {
    "last_modified": "Fri, 24 Jul 2026 08:26:29 GMT"
  },
  "https://www.bilanz.ch/sitemap-articles-time-limited-2026-06.xml": {
    "last_modified": "Tue, 30 Jun 2026 14:05:20 GMT",
    "etag": "\"54c8c9f1218fbd2ffaac78896b4da333\""
  },
  "https://partner-feeds.publishing.tamedia.ch/rss/derbund/": {
    "etag": "W/\"ef0c-CKFRcgLv8yqS/kOrcH2E64tSKlw\""
  },
  "https://partner-feeds.publishing.tamedia.ch/rss/bazonline/": {
    "etag": "W/\"e5a3-0yOUMbR+uUYE2FZ9Of9cjoNHPXU\""
  },
  "https://www.woz.ch/sitemaps/editorial_content/sitemap.xml": {
    "last_modified": "Fri, 24 Jul 2026 08:21:30 GMT",
    "etag": "\"1784881290\""
  },
  "https://www.woz.ch/sitemaps/editorial_content/sitemap.xml?page=15": {
    "last_modified": "Fri, 24 Jul 2026 08:21:30 GMT",
    "etag": "\"1784881290\""
  },
  "https://www.freiburger-nachrichten.ch/sitemap_latest_news.xml": {
    "etag": "W/\"2d2f8-MK90V8jVSjvwVhWN2qYmCAsTpbc\""
  },
  "https://www.woz.ch/sitemaps/editorial_content/sitemap.xml?page=14": {
    "last_modified": "Wed, 22 Jul 2026 11:10:55 GMT",
    "etag": "\"1784718655\""
  },
  "https://www.shn.ch/rss.xml": {
    "last_modified": "Fri, 24 Jul 2026 08:30:27 GMT",
    "etag": "W/\"1784881827-gzip\""
  },
  "https://schweizermonat.ch/feed/": {
    "last_modified": "Mon, 20 Jul 2026 12:49:38 GMT",
    "etag": "\"7c05e8e18d9b51aeee2b30c61f84e331\""
  },
  "https://www.bote.ch/googlenews.sitemap.xml": {
    "last_modified": "Fri, 24 Jul 2026 08:31:01 GMT",
    "etag": "\"1784881861\""
  },
  "https://www.bilanz.ch/sitemap-articles-time-limited-2026-07.xml": {
    "last_modified": "Fri, 24 Jul 2026 08:30:52 GMT",
    "etag": "\"38db134b9d691c94d3f0b8b7c3444e99\""
  },
  "https://www.woz.ch/sitemaps/editorial_content/sitemap.xml?page=12": {
    "last_modified": "Sat, 18 Jul 2026 23:09:19 GMT",
    "etag": "\"1784416159\""
  },
  "https://www.woz.ch/sitemaps/editorial_content/sitemap.xml?page=13": {
    "last_modified": "Sun, 19 Jul 2026 09:46:02 GMT",
    "etag": "\"1784454362\""
  }
}